pastify/__init__.py
pastify/app/RESPONSES.py
pastify/app/__init__.py
pastify/app/defaults.py
pastify/app/error.py
pastify/app/handler.py
pastify/app/main.py
pastify/app/router.py
pastify/dev/__init__.py
pastify/dev/watch.py
pastify/middleware/__init__.py
pastify/middleware/json_parser.py
pastify/utils/__init__.py
pastify/utils/message.py
pastify-0.1.2.dist-info/LICENSE
pastify-0.1.2.dist-info/METADATA
pastify-0.1.2.dist-info/WHEEL
pastify-0.1.2.dist-info/top_level.txt
pastify-0.1.2.dist-info/RECORD
