Metadata-Version: 2.1
Name: pastify
Version: 0.1.2
Summary: Pastify is a minimalistic clone of web dev frameworks like flask and express for creating web servers, having all the essential features of a webD framework
Home-page: https://github.com/tusharsinghbisht/pastify
Author: Tushar Singh Bisht
Author-email: aabisht2006@gmail.com
Classifier: Programming Language :: Python :: 3
Classifier: License :: OSI Approved :: MIT License
Classifier: Operating System :: OS Independent
Requires-Python: >=3.6
License-File: LICENSE
Requires-Dist: setuptools
